instagraal/__init__.py
instagraal/cuda_lib_gl_single.py
instagraal/fragment.py
instagraal/glutil.py
instagraal/gpustruct.py
instagraal/init_nuisance.py
instagraal/instagraal.py
instagraal/leastsqbound.py
instagraal/linkage.py
instagraal/log.py
instagraal/optim_rippe_curve_update.py
instagraal/parse_info_frags.py
instagraal/pyramid_sparse.py
instagraal/simu_single.py
instagraal/vector.py
instagraal/version.py
instagraal-0.1.6.data/scripts/instagraal-setup
instagraal-0.1.6.dist-info/LICENSE
instagraal-0.1.6.dist-info/METADATA
instagraal-0.1.6.dist-info/WHEEL
instagraal-0.1.6.dist-info/entry_points.txt
instagraal-0.1.6.dist-info/top_level.txt
instagraal-0.1.6.dist-info/RECORD
